typeset/__init__.py
typeset-0.0.0a1.dist-info/WHEEL
typeset-0.0.0a1.dist-info/entry_points.txt
typeset-0.0.0a1.dist-info/METADATA
typeset-0.0.0a1.dist-info/RECORD
