Metadata-Version: 2.3
Name: typeset
Version: 0.0.0a1
Summary: This project is coming soon.
Author: Zanie Blue
Author-email: Zanie Blue <contact@zanie.dev>
Requires-Python: >=3.13
